LICENSE.txt
README.md
setup.cfg
setup.py
dataParse/__init__.py
dataParse/parse.py
dataParse.egg-info/PKG-INFO
dataParse.egg-info/SOURCES.txt
dataParse.egg-info/dependency_links.txt
dataParse.egg-info/requires.txt
dataParse.egg-info/top_level.txt