Metadata-Version: 2.1
Name: dataParse
Version: 0.1
Summary: data parding for Image Classification datasets
Home-page: https://github.com/azatcelik/dataParse
Download-URL: https://github.com/azatcelik/dataParse/archive/refs/tags/dataset.tar.gz
Author: Azat ÇELİK
Author-email: azatcellk@hotmail.com
License: MIT
Keywords: AI,IMAGECLASSIFICATION,MACHINELEARNING,DATASETS
Classifier: Development Status :: 3 - Alpha
Classifier: Intended Audience :: Developers
Classifier: Topic :: Software Development :: Build Tools
Classifier: License :: OSI Approved :: MIT License
Classifier: Programming Language :: Python :: 3
Classifier: Programming Language :: Python :: 3.4
Classifier: Programming Language :: Python :: 3.5
Classifier: Programming Language :: Python :: 3.6
Classifier: Programming Language :: Python :: 3.7
Classifier: Programming Language :: Python :: 3.8
License-File: LICENSE.txt
